pydawa/__init__.py
pydawa/dawa.py
pydawa/geokoder.py
pydawa-0.5.1.dist-info/WHEEL
pydawa-0.5.1.dist-info/METADATA
pydawa-0.5.1.dist-info/RECORD
