Metadata-Version: 2.1
Name: pydawa
Version: 0.5.1
Summary: En API wrapper omkring Danmarks Adressers Web API
Home-page: https://github.com/danielarnason/pydawa.git
License: GPL-3.0-or-later
Author: Daníel Örn Árnason
Author-email: danielarnason85@gmail.com
Requires-Python: >=3.8,<4.0
Classifier: License :: OSI Approved :: GNU General Public License v3 or later (GPLv3+)
Classifier: Programming Language :: Python :: 3
Classifier: Programming Language :: Python :: 3.8
Requires-Dist: openpyxl (>=3.0.3,<4.0.0)
Requires-Dist: pandas (>=1.0.3,<2.0.0)
Requires-Dist: requests (>=2.23.0,<3.0.0)
Requires-Dist: xlrd (>=1.2.0,<2.0.0)
Project-URL: Repository, https://github.com/danielarnason/pydawa.git
